{
    "parent": "ecomod:ecomod/root",
    "rewards": {
        "recipes": [
          "ecomod:advanced_filter_core",
          "ecomod:analyzer_core",
          "ecomod:vent"
        ]
    },
    "display": {
        "icon": {
            "item": "ecomod:core",
            "data": 0
        },
        "title": {
            "translate": "achievement.ecomod.filter_core"
        },
        "description": {
            "translate": "achievement.ecomod.filter_core.desc"
        },
        "show_toast": true,
        "announce_to_chat": true
    },
    "criteria": {
        "filter": {
            "trigger": "minecraft:inventory_changed",
            "conditions": {
                "items": [
                    {
                        "item": "ecomod:core",
                        "data": 0
                    }
                ]
            }
        }
    },
    "requirements": [["filter"]]
}